{"credit":"Made with Blockbench","texture_size":[32,32],"textures":{"particle":"hideaway:particles/tag80k","10_x256":"hideaway:obs/na_dlk","9_x256":"hideaway:obs/3ng0ma","7_x1024":"hideaway:obs/h8il2u","5_x1024":"hideaway:obs/pl66af"},"elements":[{"from":[7,14,4],"to":[9,16,9],"rotation":{"angle":0,"axis":"y","origin":[0,15,0]},"faces":{"north":{"uv":[7.875,1.375,8,1.5],"texture":"#10_x256","tintindex":0},"east":{"uv":[5.625,9.625,5.9375,9.75],"texture":"#9_x256","tintindex":0},"south":{"uv":[8,1.375,8.125,1.5],"texture":"#10_x256","tintindex":0},"west":{"uv":[5.9375,9.625,6.25,9.75],"texture":"#9_x256","tintindex":0},"up":{"uv":[13.421875,10.46875,13.390625,10.390625],"texture":"#7_x1024","tintindex":0},"down":{"uv":[13.453125,10.390625,13.421875,10.46875],"texture":"#7_x1024","tintindex":0}}},{"from":[7.5,14.5,2],"to":[8.5,15.5,4],"rotation":{"angle":0,"axis":"y","origin":[0,15,0]},"faces":{"north":{"uv":[2.1875,15.5,2.25,15.5625],"texture":"#10_x256"},"east":{"uv":[12.625,13.9375,12.75,14],"texture":"#10_x256"},"west":{"uv":[12.75,13.9375,12.875,14],"texture":"#10_x256"},"up":{"uv":[6.25,5.875,6.1875,5.75],"texture":"#10_x256"},"down":{"uv":[6.3125,5.75,6.25,5.875],"texture":"#10_x256"}}},{"from":[7.5,-0.5,2],"to":[8.5,14.5,3],"rotation":{"angle":0,"axis":"y","origin":[0,15,0]},"faces":{"north":{"uv":[14.546875,2.953125,14.5625,3.1875],"texture":"#5_x1024"},"east":{"uv":[14.5625,2.953125,14.578125,3.1875],"texture":"#5_x1024"},"south":{"uv":[14.578125,2.953125,14.59375,3.1875],"texture":"#5_x1024"},"west":{"uv":[14.59375,2.953125,14.609375,3.1875],"texture":"#5_x1024"}}},{"from":[8,-0.5,3],"to":[8,14.5,7],"rotation":{"angle":0,"axis":"y","origin":[0,15,0]},"faces":{"east":{"uv":[1.609375,2.953125,1.671875,3.1875],"texture":"#5_x1024"},"west":{"uv":[1.671875,2.953125,1.734375,3.1875],"texture":"#5_x1024"}}},{"from":[7,6.5,1.5],"to":[9,7.5,3.5],"rotation":{"angle":0,"axis":"y","origin":[0,15,0]},"faces":{"north":{"uv":[12.875,13.9375,13,14],"texture":"#10_x256","tintindex":0},"east":{"uv":[13,13.9375,13.125,14],"texture":"#10_x256","tintindex":0},"south":{"uv":[13.125,13.9375,13.25,14],"texture":"#10_x256","tintindex":0},"west":{"uv":[13.25,13.9375,13.375,14],"texture":"#10_x256","tintindex":0},"up":{"uv":[8.25,1.5,8.125,1.375],"texture":"#10_x256","tintindex":0},"down":{"uv":[8.375,1.375,8.25,1.5],"texture":"#10_x256","tintindex":0}}},{"from":[6.5,7.5,0],"to":[9.5,13.5,2],"rotation":{"angle":0,"axis":"y","origin":[0,15,0]},"faces":{"north":{"uv":[1.3125,7.046875,1.359375,7.140625],"texture":"#7_x1024"},"east":{"uv":[9.3125,7.140625,9.34375,7.234375],"texture":"#7_x1024"},"south":{"uv":[1.359375,7.046875,1.40625,7.140625],"texture":"#7_x1024"},"west":{"uv":[9.34375,7.140625,9.375,7.234375],"texture":"#7_x1024"},"up":{"uv":[14.0625,14.25,13.875,14.125],"texture":"#9_x256"},"down":{"uv":[14.25,14.125,14.0625,14.25],"texture":"#9_x256"}}},{"from":[4.5,-2.82792,-9.70323],"to":[5.5,-0.82792,-2.70323],"rotation":{"angle":-22.5,"axis":"x","origin":[-6,12.67208,-5.70323]},"faces":{"north":{"uv":[6.3125,5.75,6.375,5.875],"texture":"#10_x256","tintindex":0},"east":{"uv":[2.625,4.875,3.0625,5],"texture":"#9_x256","tintindex":0},"south":{"uv":[6.375,5.75,6.4375,5.875],"texture":"#10_x256","tintindex":0},"west":{"uv":[3.0625,4.875,3.5,5],"texture":"#9_x256","tintindex":0},"up":{"uv":[15.765625,2.625,15.75,2.515625],"texture":"#7_x1024","tintindex":0},"down":{"uv":[15.78125,2.515625,15.765625,2.625],"texture":"#7_x1024","tintindex":0}}},{"from":[5.5,-0.82792,-8.70323],"to":[10.5,-0.82792,-3.70323],"rotation":{"angle":-22.5,"axis":"x","origin":[-6,12.67208,-5.70323]},"faces":{"up":{"uv":[2.421875,9.6875,2.34375,9.609375],"texture":"#7_x1024"},"down":{"uv":[2.5,9.609375,2.421875,9.6875],"texture":"#7_x1024"}}},{"from":[7.5,-1.32792,-6.70323],"to":[8.5,-0.32792,-5.70323],"rotation":{"angle":-22.5,"axis":"x","origin":[-6,12.67208,-5.70323]},"faces":{"north":{"uv":[2.25,15.5,2.3125,15.5625],"texture":"#10_x256","tintindex":0},"east":{"uv":[2.3125,15.5,2.375,15.5625],"texture":"#10_x256","tintindex":0},"south":{"uv":[2.375,15.5,2.4375,15.5625],"texture":"#10_x256","tintindex":0},"west":{"uv":[2.4375,15.5,2.5,15.5625],"texture":"#10_x256","tintindex":0},"up":{"uv":[2.5625,15.5625,2.5,15.5],"texture":"#10_x256","tintindex":0},"down":{"uv":[2.625,15.5,2.5625,15.5625],"texture":"#10_x256","tintindex":0}}},{"from":[5.5,-2.82792,-9.70323],"to":[10.5,-0.82792,-8.70323],"rotation":{"angle":-22.5,"axis":"x","origin":[-6,12.67208,-5.70323]},"faces":{"north":{"uv":[6.25,9.625,6.5625,9.75],"texture":"#9_x256","tintindex":0},"south":{"uv":[6.5625,9.625,6.875,9.75],"texture":"#9_x256","tintindex":0},"up":{"uv":[0.9375,10.3125,0.625,10.25],"texture":"#10_x256","tintindex":0},"down":{"uv":[1.25,10.25,0.9375,10.3125],"texture":"#10_x256","tintindex":0}}},{"from":[5.5,-2.82792,-3.70323],"to":[10.5,-0.82792,-2.70323],"rotation":{"angle":-22.5,"axis":"x","origin":[-6,12.67208,-5.70323]},"faces":{"north":{"uv":[6.875,9.625,7.1875,9.75],"texture":"#9_x256","tintindex":0},"south":{"uv":[7.1875,9.625,7.5,9.75],"texture":"#9_x256","tintindex":0},"up":{"uv":[1.5625,10.3125,1.25,10.25],"texture":"#10_x256","tintindex":0},"down":{"uv":[1.875,10.25,1.5625,10.3125],"texture":"#10_x256","tintindex":0}}},{"from":[10.5,-2.82792,-9.70323],"to":[11.5,-0.82792,-2.70323],"rotation":{"angle":-22.5,"axis":"x","origin":[-6,12.67208,-5.70323]},"faces":{"north":{"uv":[6.4375,5.75,6.5,5.875],"texture":"#10_x256","tintindex":0},"east":{"uv":[3.5,4.875,3.9375,5],"texture":"#9_x256","tintindex":0},"south":{"uv":[6.5,5.75,6.5625,5.875],"texture":"#10_x256","tintindex":0},"west":{"uv":[3.9375,4.875,4.375,5],"texture":"#9_x256","tintindex":0},"up":{"uv":[15.796875,2.625,15.78125,2.515625],"texture":"#7_x1024","tintindex":0},"down":{"uv":[15.8125,2.515625,15.796875,2.625],"texture":"#7_x1024","tintindex":0}}},{"from":[1,0,16],"to":[15,15,16],"faces":{"south":{"uv":[6.421875,2.25,6.640625,2.484375],"texture":"#5_x1024"}}},{"from":[1,1,16],"to":[15,17,16],"faces":{"south":{"uv":[12.28125,0.5,12.5,0.75],"texture":"#5_x1024","tintindex":0}}}],"display":{"thirdperson_righthand":{"rotation":[90,0,0],"translation":[0,-2,-7]},"thirdperson_lefthand":{"rotation":[90,-5,0],"translation":[0,-2,-7]},"firstperson_righthand":{"rotation":[30,5,-10],"translation":[0,-1,0.75]},"firstperson_lefthand":{"rotation":[30,5,-10],"translation":[0,-1,0.75]}},"parent":"hideaway:obs/lll8on"}