{"textures":{"particle":"hideaway:particles/qhvbhk","7_x1024":"hideaway:obs/h8il2u","3_x1024":"hideaway:obs/2eldst"},"elements":[{"from":[1.75,5.25,1.75],"to":[14.25,11.75,11.25],"rotation":{"angle":22.5,"axis":"x","origin":[8,8.5,6.5]},"faces":{"north":{"uv":[11.640625,4.234375,11.828125,4.328125],"texture":"#7_x1024"},"east":{"uv":[15.859375,7.578125,16,7.671875],"texture":"#3_x1024"},"west":{"uv":[12.34375,4.796875,12.484375,4.890625],"texture":"#7_x1024"}}}],"display":{"head":{"rotation":[0,180,0]}}}