{"credit":"Made with Blockbench","parent":"hideaway:obs/lll8on","texture_size":[64,64],"textures":{"particle":"hideaway:particles/kb8oq1","5_x1024":"hideaway:obs/pl66af","7_x1024":"hideaway:obs/h8il2u","4_x1024":"hideaway:obs/o8okc2","10_x256":"hideaway:obs/na_dlk","8_x512":"hideaway:obs/mh52_-"},"elements":[{"from":[8,16,2.5],"to":[8,32,13.5],"rotation":{"angle":45,"axis":"y","origin":[8,10,8]},"faces":{"east":{"uv":[10.390625,1.25,10.5625,1.5],"texture":"#5_x1024"},"west":{"uv":[10.390625,1.25,10.5625,1.5],"texture":"#5_x1024"}}},{"from":[2.5,16,8],"to":[13.5,32,8],"rotation":{"angle":45,"axis":"y","origin":[8,10,8]},"faces":{"north":{"uv":[10.390625,1.25,10.5625,1.5],"texture":"#5_x1024"},"south":{"uv":[10.390625,1.25,10.5625,1.5],"texture":"#5_x1024"}}},{"from":[2.5,16,8],"to":[13.5,32,8],"rotation":{"angle":45,"axis":"y","origin":[8,10,8]},"faces":{"north":{"uv":[10.5625,1.25,10.734375,1.5],"texture":"#5_x1024","tintindex":0},"south":{"uv":[10.5625,1.25,10.734375,1.5],"texture":"#5_x1024","tintindex":0}}},{"from":[2.5,16,8],"to":[13.5,32,8],"rotation":{"angle":-45,"axis":"y","origin":[8,10,8]},"faces":{"north":{"uv":[10.5625,1.25,10.734375,1.5],"texture":"#5_x1024","tintindex":0},"south":{"uv":[10.5625,1.25,10.734375,1.5],"texture":"#5_x1024","tintindex":0}}},{"from":[8.5,-7,8],"to":[12.5,-1,8],"rotation":{"angle":0,"axis":"y","origin":[8,10,8]},"faces":{"north":{"uv":[0.625,6.953125,0.5625,6.859375],"texture":"#7_x1024","tintindex":0},"south":{"uv":[0.625,6.953125,0.6875,6.859375],"texture":"#7_x1024","tintindex":0}}},{"from":[3.5,-7,8],"to":[7.5,-1,8],"rotation":{"angle":0,"axis":"y","origin":[8,10,8]},"faces":{"north":{"uv":[0.625,6.953125,0.6875,6.859375],"texture":"#7_x1024","tintindex":0},"south":{"uv":[0.625,6.953125,0.5625,6.859375],"texture":"#7_x1024","tintindex":0}}},{"from":[8,-7,3.5],"to":[8,-1,7.5],"rotation":{"angle":0,"axis":"y","origin":[8,10,8]},"faces":{"east":{"uv":[0.625,6.953125,0.6875,6.859375],"texture":"#7_x1024","tintindex":0},"west":{"uv":[0.625,6.953125,0.5625,6.859375],"texture":"#7_x1024","tintindex":0}}},{"from":[8,-7,8.5],"to":[8,-1,12.5],"rotation":{"angle":0,"axis":"y","origin":[8,10,8]},"faces":{"east":{"uv":[0.625,6.953125,0.5625,6.859375],"texture":"#7_x1024","tintindex":0},"west":{"uv":[0.625,6.953125,0.6875,6.859375],"texture":"#7_x1024","tintindex":0}}},{"from":[7.5,-6,7.5],"to":[8.5,15,8.5],"rotation":{"angle":45,"axis":"y","origin":[8,10,8]},"faces":{"north":{"uv":[2.640625,1.328125,2.65625,1.65625],"texture":"#4_x1024","tintindex":0},"east":{"uv":[2.640625,1.328125,2.65625,1.65625],"texture":"#4_x1024","tintindex":0},"south":{"uv":[2.640625,1.328125,2.65625,1.65625],"texture":"#4_x1024","tintindex":0},"west":{"uv":[2.640625,1.328125,2.65625,1.65625],"texture":"#4_x1024","tintindex":0},"down":{"uv":[7.3125,15.5,7.375,15.5625],"rotation":90,"texture":"#10_x256","tintindex":0}}},{"from":[8,10,2.5],"to":[8,16,13.5],"rotation":{"angle":45,"axis":"y","origin":[8,10,8]},"faces":{"east":{"uv":[7.8125,4.515625,7.984375,4.609375],"texture":"#7_x1024","tintindex":0},"west":{"uv":[8.15625,4.515625,7.984375,4.609375],"texture":"#7_x1024","tintindex":0}}},{"from":[2.5,10,8],"to":[13.5,16,8],"rotation":{"angle":45,"axis":"y","origin":[8,10,8]},"faces":{"south":{"uv":[7.8125,4.515625,7.984375,4.609375],"texture":"#7_x1024","tintindex":0}}},{"from":[6.5,15,6.5],"to":[9.5,18,9.5],"rotation":{"angle":45,"axis":"y","origin":[8,10,8]},"faces":{"north":{"uv":[9.9375,6.84375,10.03125,6.9375],"texture":"#8_x512","tintindex":0},"east":{"uv":[9.9375,6.84375,10.03125,6.9375],"texture":"#8_x512","tintindex":0},"south":{"uv":[9.9375,6.84375,10.03125,6.9375],"texture":"#8_x512","tintindex":0},"west":{"uv":[9.9375,6.84375,10.03125,6.9375],"texture":"#8_x512","tintindex":0},"down":{"uv":[10.03125,6.84375,10.125,6.9375],"rotation":90,"texture":"#8_x512","tintindex":0}}},{"from":[7.5,-6,7.5],"to":[8.5,15,8.5],"rotation":{"angle":45,"axis":"y","origin":[8,10,8]},"faces":{"north":{"uv":[2.65625,1.328125,2.671875,1.65625],"texture":"#4_x1024"},"east":{"uv":[2.65625,1.328125,2.671875,1.65625],"texture":"#4_x1024"},"south":{"uv":[2.65625,1.328125,2.671875,1.65625],"texture":"#4_x1024"},"west":{"uv":[2.65625,1.328125,2.671875,1.65625],"texture":"#4_x1024"}}},{"from":[6.5,15,6.5],"to":[9.5,18,9.5],"rotation":{"angle":45,"axis":"y","origin":[8,10,8]},"faces":{"north":{"uv":[10.125,6.84375,10.21875,6.9375],"texture":"#8_x512"},"east":{"uv":[10.125,6.84375,10.21875,6.9375],"texture":"#8_x512"},"south":{"uv":[10.125,6.84375,10.21875,6.9375],"texture":"#8_x512"},"west":{"uv":[10.125,6.84375,10.21875,6.9375],"texture":"#8_x512"},"up":{"uv":[10.21875,6.84375,10.3125,6.9375],"rotation":270,"texture":"#8_x512"}}},{"from":[2,0,16],"to":[17,17,16],"faces":{"south":{"uv":[1.484375,9.625,1.71875,9.890625],"texture":"#4_x1024"}}},{"from":[0,1,16],"to":[13,14,16],"faces":{"south":{"uv":[6.296875,8.78125,6.5,8.984375],"texture":"#5_x1024","tintindex":0}}}],"display":{"thirdperson_righthand":{"rotation":[23.75,0,0],"translation":[1,2,2.5]},"thirdperson_lefthand":{"rotation":[23.75,0,0],"translation":[1,2,2.5]},"firstperson_lefthand":{"rotation":[-22,-7,0],"translation":[10.5,-17,2.5]}},"groups":[{"name":"group","origin":[-6,0,0],"color":0,"nbt":"{}","children":[0,1,2,3,{"name":"group","origin":[8,10,8],"color":0,"nbt":"{}","children":[4,5,6,7,8,9,10,11]},12,13]}]}