{"credit": "Made with Blockbench", "parent": "hideaway:obs/07imlo", "texture_size": [128, 128], "textures": {"particle": "genesicore:collection/kb8oq1.png", "4_x1024": "genesicore:collection/o8okc2.png", "5_x1024": "genesicore:collection/pl66af.png", "6_x1024": "genesicore:collection/pr1qh8.png", "0_x2048": "genesicore:collection/vjud5-.png"}, "elements": [{"from": [9.273752, 5.6, 6.773752], "to": [11.373752, 7.6, 8.773752], "rotation": {"angle": 0, "axis": "y", "origin": [8.8, 7.440156, 7.773752]}, "faces": {"north": {"uv": [1.015625, 2.59375, 1.34375, 2.90625], "texture": "#4_x1024"}, "south": {"uv": [1.34375, 2.59375, 1.671875, 2.90625], "texture": "#4_x1024"}, "west": {"uv": [7.1875, 3.53125, 7.5, 3.84375], "texture": "#4_x1024"}, "up": {"uv": [11.734375, 1, 11.421875, 0.671875], "rotation": 90, "texture": "#4_x1024"}, "down": {"uv": [12.046875, 0.671875, 11.734375, 1], "rotation": 270, "texture": "#4_x1024"}}}, {"name": "colourable", "from": [9.273752, 5.6, 6.773752], "to": [11.373752, 7.6, 8.773752], "rotation": {"angle": 0, "axis": "y", "origin": [8.8, 7.440156, 7.773752]}, "faces": {"north": {"uv": [1.671875, 2.59375, 2, 2.90625], "texture": "#4_x1024", "tintindex": 0}, "east": {"uv": [7.5, 3.53125, 7.8125, 3.84375], "texture": "#4_x1024", "tintindex": 0}, "south": {"uv": [2, 2.59375, 2.328125, 2.90625], "texture": "#4_x1024", "tintindex": 0}, "up": {"uv": [12.359375, 1, 12.046875, 0.671875], "rotation": 90, "texture": "#4_x1024", "tintindex": 0}, "down": {"uv": [12.671875, 0.671875, 12.359375, 1], "rotation": 270, "texture": "#4_x1024", "tintindex": 0}}}, {"name": "colourable", "from": [11.373752, 5.6, 7.773752], "to": [12.673752, 7.6, 7.773752], "rotation": {"angle": 0, "axis": "y", "origin": [8.8, 7.440156, 7.773752]}, "faces": {"north": {"uv": [2.734375, 4.15625, 2.9375, 4.46875], "texture": "#4_x1024", "tintindex": 0}, "south": {"uv": [2.9375, 4.15625, 3.140625, 4.46875], "texture": "#4_x1024", "tintindex": 0}}}, {"from": [8.980576, 6.02961, 6.973752], "to": [9.880576, 7.62961, 8.573752], "rotation": {"angle": -22.5, "axis": "z", "origin": [8.8, 7.440156, 7.773752]}, "faces": {"north": {"uv": [10.796875, 1.5, 10.9375, 1.75], "texture": "#5_x1024"}, "east": {"uv": [12.5, 0.25, 12.75, 0.5], "texture": "#5_x1024"}, "south": {"uv": [10.9375, 1.5, 11.078125, 1.75], "texture": "#5_x1024"}, "west": {"uv": [12.75, 0.25, 13, 0.5], "texture": "#5_x1024"}, "up": {"uv": [9, 8.359375, 8.75, 8.21875], "rotation": 90, "texture": "#6_x1024"}, "down": {"uv": [9.25, 8.21875, 9, 8.359375], "rotation": 270, "texture": "#6_x1024"}}}, {"from": [3.280576, 6.22961, 7.173752], "to": [10.580576, 7.42961, 8.373752], "rotation": {"angle": -22.5, "axis": "z", "origin": [8.8, 7.440156, 7.773752]}, "faces": {"north": {"uv": [10.921875, 10, 12.0625, 10.1875], "texture": "#5_x1024"}, "east": {"uv": [5.8125, 13.765625, 6, 13.953125], "texture": "#5_x1024"}, "south": {"uv": [12.0625, 10, 13.203125, 10.1875], "texture": "#5_x1024"}, "west": {"uv": [6, 13.765625, 6.1875, 13.953125], "texture": "#5_x1024"}, "up": {"uv": [15.8359375, 8.625, 15.7421875, 8.0546875], "rotation": 90, "texture": "#0_x2048"}, "down": {"uv": [15.9296875, 8.0546875, 15.8359375, 8.625], "rotation": 270, "texture": "#0_x2048"}}}], "gui_light": "front", "display": {"gui": {"rotation": [30, 225, 0], "scale": [3.125, 3.125, 3.125]}}, "groups": [0, 1, 2, {"name": "handle", "origin": [0, 12.75, -19], "color": 0, "children": [3, 4]}]}