{"credit": "Made by Ziqqy using Blockbench", "parent": "hideaway:obs/sp6hnt", "textures": {"particle": "genesicore:collection/c0-2mb.png", "6_x1024": "genesicore:collection/pr1qh8.png", "9_x256": "genesicore:collection/3ng0ma.png", "7_x1024": "genesicore:collection/h8il2u.png", "8_x512": "genesicore:collection/mh52_-.png", "10_x256": "genesicore:collection/na_dlk.png"}, "elements": [{"from": [7.6, 7.6, 7.6], "to": [8.4, 8.4, 8.4], "rotation": {"angle": 0, "axis": "y", "origin": [7.2, 6.4, 7.2]}, "faces": {"north": {"uv": [2.375, 14.078125, 2.5, 14.203125], "texture": "#6_x1024"}, "east": {"uv": [2.5, 14.078125, 2.625, 14.203125], "texture": "#6_x1024"}, "south": {"uv": [2.625, 14.078125, 2.75, 14.203125], "texture": "#6_x1024"}, "west": {"uv": [2.75, 14.078125, 2.875, 14.203125], "texture": "#6_x1024"}, "up": {"uv": [3, 14.203125, 2.875, 14.078125], "texture": "#6_x1024"}, "down": {"uv": [3.125, 14.078125, 3, 14.203125], "texture": "#6_x1024"}}}, {"from": [7.8, 7.4, 7.8], "to": [8.2, 7.6, 8.2], "rotation": {"angle": 0, "axis": "y", "origin": [7.2, 6.4, 7.2]}, "faces": {"north": {"uv": [15, 12.25, 15.25, 12.375], "texture": "#9_x256"}, "east": {"uv": [15.25, 12.25, 15.5, 12.375], "texture": "#9_x256"}, "south": {"uv": [15.5, 12.25, 15.75, 12.375], "texture": "#9_x256"}, "west": {"uv": [15.75, 12.25, 16, 12.375], "texture": "#9_x256"}, "up": {"uv": [13, 14.0625, 12.9375, 14], "texture": "#7_x1024"}, "down": {"uv": [13.0625, 14, 13, 14.0625], "texture": "#7_x1024"}}}, {"from": [7.5, 7.2, 7.5], "to": [8.5, 7.4, 8.5], "rotation": {"angle": 0, "axis": "y", "origin": [7.2, 6.4, 7.2]}, "faces": {"north": {"uv": [14.375, 0.25, 15, 0.375], "texture": "#9_x256"}, "east": {"uv": [15, 0.25, 15.625, 0.375], "texture": "#9_x256"}, "south": {"uv": [0, 0.375, 0.625, 0.5], "texture": "#9_x256"}, "west": {"uv": [0.625, 0.375, 1.25, 0.5], "texture": "#9_x256"}, "up": {"uv": [9.21875, 5.640625, 9.0625, 5.484375], "texture": "#6_x1024"}, "down": {"uv": [9.375, 5.484375, 9.21875, 5.640625], "texture": "#6_x1024"}}}, {"from": [7.5, 8, 7.5], "to": [8.5, 8.5, 8.5], "rotation": {"angle": 0, "axis": "y", "origin": [7.6, 8.3, 7.5]}, "faces": {"north": {"uv": [3.90625, 8.671875, 4.0625, 8.75], "texture": "#7_x1024"}, "east": {"uv": [4.21875, 8.671875, 4.0625, 8.75], "texture": "#7_x1024"}, "south": {"uv": [4.21875, 8.671875, 4.375, 8.75], "texture": "#7_x1024"}, "west": {"uv": [4.375, 8.671875, 4.53125, 8.75], "texture": "#7_x1024"}, "up": {"uv": [9.21875, 5.640625, 9.0625, 5.484375], "texture": "#6_x1024"}, "down": {"uv": [9.375, 5.484375, 9.21875, 5.640625], "texture": "#6_x1024"}}}, {"from": [7.9, 7.9, 7.399], "to": [8.1, 8.2, 7.599], "rotation": {"angle": 0, "axis": "y", "origin": [8, 8.05, 7.45]}, "faces": {"north": {"uv": [12.5, 8.71875, 12.5625, 8.8125], "texture": "#8_x512"}, "east": {"uv": [12.5625, 8.71875, 12.625, 8.8125], "texture": "#8_x512"}, "south": {"uv": [12.625, 8.71875, 12.6875, 8.8125], "texture": "#8_x512"}, "west": {"uv": [12.75, 8.71875, 12.6875, 8.8125], "texture": "#8_x512"}, "up": {"uv": [14.5, 3.375, 14.375, 3.25], "texture": "#10_x256"}, "down": {"uv": [14.625, 3.25, 14.5, 3.375], "texture": "#10_x256"}}}, {"from": [7.4, 7.95782, 8.18796], "to": [7.6, 8.25782, 8.58796], "rotation": {"angle": -22.5, "axis": "x", "origin": [7.501, 8.05782, 8.43796]}, "faces": {"north": {"uv": [12.75, 8.71875, 12.8125, 8.8125], "texture": "#8_x512"}, "east": {"uv": [3.375, 6.09375, 3.25, 6.1875], "texture": "#8_x512"}, "south": {"uv": [12.8125, 8.71875, 12.875, 8.8125], "texture": "#8_x512"}, "west": {"uv": [3.375, 6.09375, 3.5, 6.1875], "texture": "#8_x512"}, "up": {"uv": [2.21875, 14.75, 2.1875, 14.6875], "texture": "#7_x1024"}, "down": {"uv": [2.25, 14.6875, 2.21875, 14.75], "texture": "#7_x1024"}}}, {"from": [7.4, 7.85782, 8.08796], "to": [7.6, 7.95782, 8.58796], "rotation": {"angle": -22.5, "axis": "x", "origin": [7.501, 8.05782, 8.43796]}, "faces": {"north": {"uv": [6.625, 14.625, 6.5, 14.5625], "texture": "#10_x256"}, "east": {"uv": [10.390625, 10.625, 10.375, 10.546875], "rotation": 90, "texture": "#7_x1024"}, "south": {"uv": [6.75, 14.625, 6.625, 14.5625], "texture": "#10_x256"}, "west": {"uv": [10.40625, 10.546875, 10.390625, 10.625], "rotation": 90, "texture": "#7_x1024"}, "up": {"uv": [5.90625, 10.546875, 5.875, 10.46875], "texture": "#7_x1024"}, "down": {"uv": [5.9375, 10.46875, 5.90625, 10.546875], "texture": "#7_x1024"}}}, {"from": [7.399, 7.8, 7.8], "to": [7.599, 8.2, 8], "rotation": {"angle": 22.5, "axis": "x", "origin": [7.5, 8, 7.9]}, "faces": {"north": {"uv": [2.25, 14.6875, 2.28125, 14.75], "texture": "#7_x1024"}, "east": {"uv": [2.28125, 14.6875, 2.3125, 14.75], "texture": "#7_x1024"}, "south": {"uv": [2.34375, 14.6875, 2.3125, 14.75], "texture": "#7_x1024"}, "west": {"uv": [2.34375, 14.6875, 2.375, 14.75], "texture": "#7_x1024"}, "up": {"uv": [14.75, 3.375, 14.625, 3.25], "texture": "#10_x256"}, "down": {"uv": [14.875, 3.25, 14.75, 3.375], "texture": "#10_x256"}}}, {"from": [7.85, 8.34598, 8.33118], "to": [8.15, 8.64598, 8.63118], "rotation": {"angle": -22.5, "axis": "x", "origin": [8, 8.49598, 8.48118]}, "faces": {"north": {"uv": [11.34375, 7.5, 11.25, 7.59375], "texture": "#8_x512"}, "east": {"uv": [11.34375, 7.5, 11.4375, 7.59375], "texture": "#8_x512"}, "south": {"uv": [11.53125, 7.5, 11.4375, 7.59375], "texture": "#8_x512"}, "west": {"uv": [11.625, 7.5, 11.53125, 7.59375], "texture": "#8_x512"}, "up": {"uv": [11.71875, 7.59375, 11.625, 7.5], "texture": "#8_x512"}, "down": {"uv": [11.34375, 7.5, 11.25, 7.59375], "texture": "#8_x512"}}}, {"from": [7.2, 8.2, 7.7], "to": [7.7, 8.7, 7.9], "rotation": {"angle": 22.5, "axis": "z", "origin": [7.45, 8.45, 7.8]}, "faces": {"north": {"uv": [2.96875, 9.765625, 3.046875, 9.84375], "texture": "#7_x1024"}, "east": {"uv": [5.9375, 10.46875, 5.96875, 10.546875], "texture": "#7_x1024"}, "south": {"uv": [3.046875, 9.765625, 3.125, 9.84375], "texture": "#7_x1024"}, "west": {"uv": [6, 10.46875, 5.96875, 10.546875], "texture": "#7_x1024"}, "up": {"uv": [6, 10.46875, 5.96875, 10.546875], "rotation": 90, "texture": "#7_x1024"}, "down": {"uv": [5.9375, 10.46875, 5.96875, 10.546875], "rotation": 90, "texture": "#7_x1024"}}}, {"from": [8.401, 7.8, 7.8], "to": [8.601, 8.2, 8], "rotation": {"angle": 22.5, "axis": "x", "origin": [8.5, 8, 7.9]}, "faces": {"north": {"uv": [2.34375, 14.6875, 2.3125, 14.75], "texture": "#7_x1024"}, "east": {"uv": [2.40625, 14.6875, 2.375, 14.75], "texture": "#7_x1024"}, "south": {"uv": [2.25, 14.6875, 2.28125, 14.75], "texture": "#7_x1024"}, "west": {"uv": [2.4375, 14.6875, 2.40625, 14.75], "texture": "#7_x1024"}, "up": {"uv": [14.875, 3.375, 15, 3.25], "texture": "#10_x256"}, "down": {"uv": [15, 3.25, 15.125, 3.375], "texture": "#10_x256"}}}, {"from": [8.4, 7.85782, 8.08796], "to": [8.6, 7.95782, 8.58796], "rotation": {"angle": -22.5, "axis": "x", "origin": [8.499, 8.05782, 8.43796]}, "faces": {"north": {"uv": [6.75, 14.625, 6.875, 14.5625], "texture": "#10_x256"}, "east": {"uv": [10.421875, 10.625, 10.40625, 10.546875], "rotation": 90, "texture": "#7_x1024"}, "south": {"uv": [6.875, 14.625, 7, 14.5625], "texture": "#10_x256"}, "west": {"uv": [10.4375, 10.546875, 10.421875, 10.625], "rotation": 90, "texture": "#7_x1024"}, "up": {"uv": [6, 10.546875, 6.03125, 10.46875], "texture": "#7_x1024"}, "down": {"uv": [6.03125, 10.46875, 6.0625, 10.546875], "texture": "#7_x1024"}}}, {"from": [8.4, 7.95782, 8.18796], "to": [8.6, 8.25782, 8.58796], "rotation": {"angle": -22.5, "axis": "x", "origin": [8.499, 8.05782, 8.43796]}, "faces": {"north": {"uv": [12.9375, 8.71875, 12.875, 8.8125], "texture": "#8_x512"}, "east": {"uv": [3.375, 6.09375, 3.25, 6.1875], "texture": "#8_x512"}, "south": {"uv": [13, 8.71875, 12.9375, 8.8125], "texture": "#8_x512"}, "west": {"uv": [3.375, 6.09375, 3.5, 6.1875], "texture": "#8_x512"}, "up": {"uv": [2.4375, 14.75, 2.46875, 14.6875], "texture": "#7_x1024"}, "down": {"uv": [2.46875, 14.6875, 2.5, 14.75], "texture": "#7_x1024"}}}, {"from": [8.3, 8.2, 7.7], "to": [8.8, 8.7, 7.9], "rotation": {"angle": -22.5, "axis": "z", "origin": [8.55, 8.45, 7.8]}, "faces": {"north": {"uv": [3.203125, 9.765625, 3.125, 9.84375], "texture": "#7_x1024"}, "east": {"uv": [5.9375, 10.46875, 5.96875, 10.546875], "texture": "#7_x1024"}, "south": {"uv": [3.28125, 9.765625, 3.203125, 9.84375], "texture": "#7_x1024"}, "west": {"uv": [6, 10.46875, 5.96875, 10.546875], "texture": "#7_x1024"}, "up": {"uv": [6.09375, 10.546875, 6.0625, 10.46875], "rotation": 90, "texture": "#7_x1024"}, "down": {"uv": [6.09375, 10.546875, 6.125, 10.46875], "rotation": 90, "texture": "#7_x1024"}}}], "display": {"gui": {"rotation": [30, -135, 0], "translation": [0, 1.25, 0], "scale": [4, 4, 4]}}, "groups": [0, 1, 2, {"name": "group", "origin": [13.5, 12.5, 6], "color": 0, "nbt": "{}", "children": [3, 4, 5, 6, 7, 8, 9, 10, 11, 12, 13]}], "__credit": "Generated using Animated Java (https://animated-java.dev/)"}