{"credit":"Made by Ziqqy using Blockbench","parent":"hideaway:obs/qu-eks","texture_size":[64,64],"textures":{"particle":"hideaway:particles/2nj3q6","9_x256":"hideaway:obs/3ng0ma","6_x1024":"hideaway:obs/pr1qh8","7_x1024":"hideaway:obs/h8il2u","10_x256":"hideaway:obs/na_dlk"},"elements":[{"from":[7.6,6.4,7.6],"to":[8.4,6.6,8.4],"rotation":{"angle":0,"axis":"y","origin":[7.2,6.6,7.2]},"faces":{"north":{"uv":[8.5,3.125,9,3.25],"texture":"#9_x256"},"east":{"uv":[9,3.125,9.5,3.25],"texture":"#9_x256"},"south":{"uv":[9.5,3.125,10,3.25],"texture":"#9_x256"},"west":{"uv":[10,3.125,10.5,3.25],"texture":"#9_x256"},"up":{"uv":[13.25,13.953125,13.125,13.828125],"texture":"#6_x1024"},"down":{"uv":[13.375,13.828125,13.25,13.953125],"texture":"#6_x1024"}}},{"from":[7.9,7.6,7.9],"to":[8.1,8.7,8.1],"rotation":{"angle":0,"axis":"y","origin":[7.2,6.6,7.2]},"faces":{"north":{"uv":[4.171875,1.71875,4.203125,1.890625],"texture":"#6_x1024"},"east":{"uv":[4.203125,1.71875,4.234375,1.890625],"texture":"#6_x1024"},"south":{"uv":[4.234375,1.71875,4.265625,1.890625],"texture":"#6_x1024"},"west":{"uv":[4.265625,1.71875,4.296875,1.890625],"texture":"#6_x1024"}}},{"from":[7.9,6.6,7.9],"to":[8.1,7.1,8.1],"rotation":{"angle":0,"axis":"y","origin":[7.2,6.6,7.2]},"faces":{"north":{"uv":[4.125,10.46875,4.15625,10.546875],"texture":"#7_x1024"},"east":{"uv":[4.15625,10.46875,4.1875,10.546875],"texture":"#7_x1024"},"south":{"uv":[4.1875,10.46875,4.21875,10.546875],"texture":"#7_x1024"},"west":{"uv":[4.21875,10.46875,4.25,10.546875],"texture":"#7_x1024"}}},{"from":[7.8,8.7,7.8],"to":[8.2,8.8,8.2],"rotation":{"angle":0,"axis":"y","origin":[7.2,6.6,7.2]},"faces":{"north":{"uv":[10,11.5625,10.25,11.625],"texture":"#10_x256"},"east":{"uv":[10.25,11.5625,10.5,11.625],"texture":"#10_x256"},"south":{"uv":[10.5,11.5625,10.75,11.625],"texture":"#10_x256"},"west":{"uv":[10.75,11.5625,11,11.625],"texture":"#10_x256"},"down":{"uv":[15.125,13.9375,15.0625,14],"texture":"#7_x1024"}}},{"from":[7.7,7.1,7.9],"to":[8.3,7.6,8.1],"rotation":{"angle":0,"axis":"y","origin":[7.2,6.6,7.2]},"faces":{"north":{"uv":[11.0625,9.296875,11.15625,9.375],"texture":"#7_x1024"},"east":{"uv":[4.25,10.46875,4.28125,10.546875],"texture":"#7_x1024"},"south":{"uv":[11.15625,9.296875,11.25,9.375],"texture":"#7_x1024"},"west":{"uv":[4.28125,10.46875,4.3125,10.546875],"texture":"#7_x1024"},"up":{"uv":[2.625,7.5,2.25,7.375],"texture":"#9_x256"},"down":{"uv":[3,7.375,2.625,7.5],"texture":"#9_x256"}}},{"from":[7.5,8.8,7.5],"to":[8.5,9.7,8.5],"rotation":{"angle":0,"axis":"y","origin":[7.2,6.6,7.2]},"faces":{"north":{"uv":[1.25,8.921875,1.40625,9.0625],"texture":"#6_x1024","tintindex":0},"east":{"uv":[1.25,8.921875,1.40625,9.0625],"texture":"#6_x1024","tintindex":0},"south":{"uv":[1.25,8.921875,1.40625,9.0625],"texture":"#6_x1024","tintindex":0},"west":{"uv":[1.25,8.921875,1.40625,9.0625],"texture":"#6_x1024","tintindex":0},"up":{"uv":[1.71875,5.484375,1.5625,5.328125],"texture":"#6_x1024","tintindex":0},"down":{"uv":[1.875,5.328125,1.71875,5.484375],"texture":"#6_x1024","tintindex":0}}},{"from":[7.6,7.9,7.7],"to":[8.4,8.4,7.7],"rotation":{"angle":0,"axis":"y","origin":[7.2,6.6,7.2]},"faces":{"north":{"uv":[0.25,8.984375,0.375,9.0625],"texture":"#7_x1024"},"south":{"uv":[0.5,8.984375,0.375,9.0625],"texture":"#7_x1024"}}},{"from":[7.6,7.9,7.7],"to":[7.6,8.4,8.3],"rotation":{"angle":0,"axis":"y","origin":[8.8,6.6,7.2]},"faces":{"east":{"uv":[11.34375,9.296875,11.25,9.375],"texture":"#7_x1024"},"west":{"uv":[11.34375,9.296875,11.4375,9.375],"texture":"#7_x1024"}}},{"from":[7.6,7.9,8.3],"to":[8.4,8.4,8.3],"rotation":{"angle":0,"axis":"y","origin":[8.8,6.6,8.8]},"faces":{"north":{"uv":[0.5,8.984375,0.375,9.0625],"texture":"#7_x1024"},"south":{"uv":[0.25,8.984375,0.375,9.0625],"texture":"#7_x1024"}}},{"from":[8.4,7.9,7.7],"to":[8.4,8.4,8.3],"rotation":{"angle":0,"axis":"y","origin":[7.2,6.6,8.8]},"faces":{"east":{"uv":[11.34375,9.296875,11.4375,9.375],"texture":"#7_x1024"},"west":{"uv":[11.34375,9.296875,11.25,9.375],"texture":"#7_x1024"}}}],"display":{"gui":{"rotation":[30,-135,0],"scale":[4,4,4]}},"groups":[{"name":"group","origin":[8,8,8],"color":0,"nbt":"{}","children":[0,1,2,3,4,5,6,7,8,9]}]}