{"textures":{"particle":"hideaway:particles/ailtct","6_x1024":"hideaway:obs/pr1qh8","7_x1024":"hideaway:obs/h8il2u"},"elements":[{"from":[4.5,6,8],"to":[7.5,17,8],"rotation":{"angle":22.5,"axis":"z","origin":[6,12.5,8]},"faces":{"north":{"uv":[15.6875,1.546875,15.734375,1.71875],"texture":"#6_x1024"}}},{"from":[1.4949999999999992,7.994999999999997,7.995],"to":[4.505,14.005000000000004,8.005],"rotation":{"angle":45,"axis":"z","origin":[6,13.5,8]},"faces":{"north":{"uv":[0.328125,7.046875,0.375,7.140625],"texture":"#7_x1024"}}}],"display":{"head":{"rotation":[0,180,0]}}}