{"credit":"Made with Blockbench","parent":"hideaway:obs/501cbo","texture_size":[128,128],"textures":{"particle":"hideaway:particles/o7mn4-","1_x1024":"hideaway:obs/kj5h0k"},"elements":[{"from":[5.6,4.8,7.98],"to":[10.4,9.6,7.98],"rotation":{"angle":0,"axis":"y","origin":[8,0,7.99]},"faces":{"north":{"uv":[2.25,14.828125,3,15.578125],"texture":"#1_x1024"},"east":{"uv":[0,0,0,6],"texture":"#missing"},"south":{"uv":[3.75,14.828125,3,15.578125],"texture":"#1_x1024"},"west":{"uv":[0,0,0,6],"texture":"#missing"},"up":{"uv":[6,0,0,0],"texture":"#missing"},"down":{"uv":[6,0,0,0],"texture":"#missing"}}},{"from":[5.6,4.8,8.02],"to":[10.4,9.6,8.02],"rotation":{"angle":0,"axis":"y","origin":[8,0,7.99]},"faces":{"north":{"uv":[2.25,14.828125,3,15.578125],"texture":"#1_x1024"},"south":{"uv":[3.75,14.828125,3,15.578125],"texture":"#1_x1024"}}}],"display":{"gui":{"rotation":[30,225,0],"scale":[3.4,3.4,3.4]}},"__credit":"Generated using Animated Java (https://animated-java.dev/)"}