{"textures":{"particle":"hideaway:particles/5dbb9q","8_x512":"hideaway:obs/mh52_-","10_x256":"hideaway:obs/na_dlk"},"elements":[{"from":[5.99,4.99,7.99],"to":[10.01,8.01,9.01],"rotation":{"angle":0,"axis":"y","origin":[8,6.5,7.5]},"faces":{"north":{"uv":[13.75,5.625,13.625,5.71875],"texture":"#8_x512"},"east":{"uv":[9.28125,9.09375,9.25,9.1875],"texture":"#8_x512"},"south":{"uv":[13.875,5.625,13.75,5.71875],"texture":"#8_x512"},"west":{"uv":[9.3125,9.09375,9.28125,9.1875],"texture":"#8_x512"},"up":{"uv":[15.75,11.125,16,11.0625],"texture":"#10_x256"},"down":{"uv":[0,11.125,0.25,11.1875],"texture":"#10_x256"}}}],"display":{"head":{"rotation":[0,180,0]}}}